README.md
setup.py
vabbat/__init__.py
vabbat/__main__.py
vabbat/drawer.py
vabbat/main.py
vabbat.egg-info/PKG-INFO
vabbat.egg-info/SOURCES.txt
vabbat.egg-info/dependency_links.txt
vabbat.egg-info/entry_points.txt
vabbat.egg-info/top_level.txt